py_simple_ttk/__init__.py
py_simple_ttk/app.py
py_simple_ttk/form.py
py_simple_ttk/version.py
py_simple_ttk/assets/black_close_button.png
py_simple_ttk/assets/circle.png
py_simple_ttk/assets/copy_32_black.png
py_simple_ttk/assets/copy_32_white.png
py_simple_ttk/assets/copy_clipboard_32_black.png
py_simple_ttk/assets/copy_clipboard_32_plain_black.png
py_simple_ttk/assets/copy_clipboard_32_plain_black_bold_arrow.png
py_simple_ttk/assets/copy_clipboard_32_plain_white.png
py_simple_ttk/assets/copy_clipboard_32_plain_white_bold_arrow.png
py_simple_ttk/assets/copy_clipboard_32_white.png
py_simple_ttk/assets/eye_16_black.png
py_simple_ttk/assets/eye_16_white.png
py_simple_ttk/assets/eye_32_black.png
py_simple_ttk/assets/eye_32_white.png
py_simple_ttk/assets/file.png
py_simple_ttk/assets/folder.png
py_simple_ttk/assets/generated.zip
py_simple_ttk/assets/ico.png
py_simple_ttk/assets/lines_16_black.png
py_simple_ttk/assets/lines_16_gray.png
py_simple_ttk/assets/lines_16_white.png
py_simple_ttk/assets/pencil_32_black.png
py_simple_ttk/assets/pencil_32_white.png
py_simple_ttk/assets/profile.png
py_simple_ttk/assets/pushpin_32_active_transparent_black.png
py_simple_ttk/assets/pushpin_32_active_transparent_white.png
py_simple_ttk/assets/pushpin_32_filled_black.png
py_simple_ttk/assets/pushpin_32_filled_white.png
py_simple_ttk/assets/pushpin_32_transparent_black.png
py_simple_ttk/assets/pushpin_32_transparent_white.png
py_simple_ttk/assets/python_icon_16.png
py_simple_ttk/assets/python_icon_16_transparent_black.png
py_simple_ttk/assets/python_icon_16_transparent_gray.png
py_simple_ttk/assets/python_icon_16_transparent_white.png
py_simple_ttk/assets/test.gif
py_simple_ttk/assets/trash_16_black.png
py_simple_ttk/assets/trash_16_white.png
py_simple_ttk/assets/trash_32_black.png
py_simple_ttk/assets/trash_32_white.png
py_simple_ttk/assets/white_close_button.png
py_simple_ttk/assets/fonts/Open_Sans/LICENSE.txt
py_simple_ttk-0.2.10.dist-info/LICENSE
py_simple_ttk-0.2.10.dist-info/METADATA
py_simple_ttk-0.2.10.dist-info/WHEEL
py_simple_ttk-0.2.10.dist-info/top_level.txt
py_simple_ttk-0.2.10.dist-info/RECORD
