Metadata-Version: 2.1
Name: py-simple-ttk
Version: 0.2.10
Summary: Tkinter themes don't have to be hard.
Author-email: Andrew Spangler <AndrewSpangler@users.noreply.github.com>
License: LICENSE
Project-URL: homepage, https://GitHub.com/AndrewSpangler/py_simple_ttk/
Project-URL: bug tracker, https://GitHub.com/AndrewSpangler/py_simple_ttk/issues
Project-URL: documentation, https://GitHub.com/AndrewSpangler/py_simple_ttk/
Project-URL: repository, https://GitHub.com/AndrewSpangler/py_simple_ttk/
Classifier: Development Status :: 1 - Planning
Classifier: Environment :: Console
Classifier: License :: OSI Approved :: GNU General Public License v3 or later (GPLv3+)
Classifier: Natural Language :: English
Classifier: Operating System :: OS Independent
Classifier: Programming Language :: Python :: 3.11
Requires-Python: >=3.9
License-File: LICENSE
Requires-Dist: py-simple-lorem
